yolo_poser/__init__.py
yolo_poser/api.py
yolo_poser/autocrop.py
yolo_poser/pose_detect.py
yolo_poser/split.py
yolo_poser/sync_audio.py
yolo_poser/utils.py
yolo_poser/yolo11n-pose.pt
yolo_poser-0.1.18.dist-info/entry_points.txt
yolo_poser-0.1.18.dist-info/licenses/LICENSE
yolo_poser-0.1.18.dist-info/WHEEL
yolo_poser-0.1.18.dist-info/METADATA
yolo_poser-0.1.18.dist-info/RECORD
