Metadata-Version: 2.4
Name: yolo-poser
Version: 0.1.18
Summary: YOLO-based human pose detection and visualization tool
Author: [Tom Dyson]
Requires-Python: >=3.8,<3.13
Classifier: Development Status :: 3 - Alpha
Classifier: Intended Audience :: Developers
Classifier: License :: OSI Approved :: MIT License
Classifier: Programming Language :: Python :: 3
Classifier: Programming Language :: Python :: 3.8
Classifier: Programming Language :: Python :: 3.9
Classifier: Programming Language :: Python :: 3.10
Classifier: Programming Language :: Python :: 3.11
Classifier: Programming Language :: Python :: 3.12
Classifier: Topic :: Multimedia :: Video
Classifier: Topic :: Scientific/Engineering :: Artificial Intelligence
License-File: LICENSE
Requires-Dist: torch>=2.0.0
Requires-Dist: ultralytics>=8.0.0
Requires-Dist: opencv-python>=4.5.0
Requires-Dist: numpy>=1.19.0
Requires-Dist: scipy>=1.7.0
Requires-Dist: fastapi>=0.68.0 ; extra == "api"
Requires-Dist: uvicorn>=0.15.0 ; extra == "api"
Requires-Dist: python-multipart>=0.0.5 ; extra == "api"
Requires-Dist: pydantic>=1.8.0 ; extra == "api"
Project-URL: Documentation, https://github.com/tomdyson/yolo-poser#readme
Project-URL: Home, https://github.com/tomdyson/yolo-poser
Project-URL: Source, https://github.com/tomdyson/yolo-poser
Provides-Extra: api
